README.md
setup.py
pulumi_neon/__init__.py
pulumi_neon/_utilities.py
pulumi_neon/provider.py
pulumi_neon/pulumi-plugin.json
pulumi_neon/py.typed
pulumi_neon.egg-info/PKG-INFO
pulumi_neon.egg-info/SOURCES.txt
pulumi_neon.egg-info/dependency_links.txt
pulumi_neon.egg-info/not-zip-safe
pulumi_neon.egg-info/requires.txt
pulumi_neon.egg-info/top_level.txt
pulumi_neon/config/__init__.py
pulumi_neon/config/__init__.pyi
pulumi_neon/config/vars.py
pulumi_neon/resource/__init__.py
pulumi_neon/resource/project.py