Metadata-Version: 2.1
Name: pulumi_neon
Version: 0.0.1b1
Summary: Pulumi Neon Provider
Home-page: https://github.com/kislerdm/pulumi-neon
License: Apache-2.0
Project-URL: Repository, https://github.com/kislerdm/pulumi-neon
Keywords: pulumi neon category/database
Requires-Python: >=3.9
Requires-Dist: parver>=0.2.1
Requires-Dist: pulumi<4.0.0,>=3.0.0
Requires-Dist: semver>=2.8.1
Requires-Dist: typing-extensions<5,>=4.11; python_version < "3.11"
